simplevideocutter/__about__.py
simplevideocutter/__init__.py
simplevideocutter/cli.py
simplevideocutter/cut.py
simplevideocutter/util.py
simplevideocutter-0.1.1.dist-info/LICENSE
simplevideocutter-0.1.1.dist-info/METADATA
simplevideocutter-0.1.1.dist-info/WHEEL
simplevideocutter-0.1.1.dist-info/entry_points.txt
simplevideocutter-0.1.1.dist-info/top_level.txt
simplevideocutter-0.1.1.dist-info/RECORD
