Metadata-Version: 2.1
Name: simplevideocutter
Version: 0.1.1
Summary: A wrapper tool around ffmpeg to simplify cutting a video (VOD) into multiple pieces.
Home-page: https://github.com/ricekab/simple-video-cutter
Author: ricekab
Author-email: contact@kevinchiytangtang.com
License: MIT License
Platform: UNKNOWN
Requires-Python: >=3.8
License-File: LICENSE
Requires-Dist: click (>=8)
Provides-Extra: gui
Requires-Dist: PySide2 ; extra == 'gui'
